mongoengine/__init__.py
mongoengine/common.py
mongoengine/connection.py
mongoengine/context_managers.py
mongoengine/dereference.py
mongoengine/document.py
mongoengine/errors.py
mongoengine/fields.py
mongoengine/mongodb_support.py
mongoengine/pymongo_support.py
mongoengine/signals.py
mongoengine/base/__init__.py
mongoengine/base/common.py
mongoengine/base/datastructures.py
mongoengine/base/document.py
mongoengine/base/fields.py
mongoengine/base/metaclasses.py
mongoengine/base/utils.py
mongoengine/queryset/__init__.py
mongoengine/queryset/base.py
mongoengine/queryset/field_list.py
mongoengine/queryset/manager.py
mongoengine/queryset/queryset.py
mongoengine/queryset/transform.py
mongoengine/queryset/visitor.py
mongoengine-0.29.1.dist-info/AUTHORS
mongoengine-0.29.1.dist-info/LICENSE
mongoengine-0.29.1.dist-info/METADATA
mongoengine-0.29.1.dist-info/WHEEL
mongoengine-0.29.1.dist-info/top_level.txt
mongoengine-0.29.1.dist-info/RECORD
