Metadata-Version: 2.1
Name: mongoengine
Version: 0.29.1
Summary: MongoEngine is a Python Object-Document Mapper for working with MongoDB.
Home-page: http://mongoengine.org/
Author: Harry Marr
Author-email: harry.marr@gmail.com
Maintainer: Bastien Gerard
Maintainer-email: bast.gerard@gmail.com
License: MIT
Download-URL: https://github.com/MongoEngine/mongoengine/tarball/master
Platform: any
Classifier: Development Status :: 5 - Production/Stable
Classifier: Intended Audience :: Developers
Classifier: License :: OSI Approved :: MIT License
Classifier: Operating System :: OS Independent
Classifier: Programming Language :: Python
Classifier: Programming Language :: Python :: 3
Classifier: Programming Language :: Python :: 3.8
Classifier: Programming Language :: Python :: 3.9
Classifier: Programming Language :: Python :: 3.10
Classifier: Programming Language :: Python :: Implementation :: CPython
Classifier: Programming Language :: Python :: Implementation :: PyPy
Classifier: Topic :: Database
Classifier: Topic :: Software Development :: Libraries :: Python Modules
Requires-Python: >=3.7
Provides-Extra: test
License-File: LICENSE
License-File: AUTHORS
